rtseason/__init__.py
rtseason/seasons.py
rtseason/tests.py
rtseason-1.1.3.dist-info/METADATA
rtseason-1.1.3.dist-info/WHEEL
rtseason-1.1.3.dist-info/top_level.txt
rtseason-1.1.3.dist-info/RECORD
