Metadata-Version: 2.1
Name: rtseason
Version: 1.1.3
Summary: Analyzing river seasonal thermal regimes in Python
Home-page: https://github.com/quantum-dan/seasonality
Author: Daniel Philippus
Author-email: daniel@dphilippus.com
Project-URL: Bug Tracker, https://github.com/quantum-dan/seasonality/issues
Classifier: Programming Language :: Python :: 3
Classifier: License :: OSI Approved :: GNU General Public License v3 (GPLv3)
Requires-Python: >=3.0
Requires-Dist: pandas
Requires-Dist: numpy
